{
    "Meta Data": {
        "1. Symbol": "603899.SH",
        "2. Last Refreshed": "2025-10-28 12:06:12",
        "3. Time Zone": "Asia/Shanghai"
    },
    "Time Series (Daily)": {
        "2025-10-27": {
            "1. open": "27.7200",
            "2. high": "27.7400",
            "3. low": "27.4900",
            "4. close": "27.5200",
            "5. volume": "3499433"
        },
        "2025-10-24": {
            "1. open": "27.8300",
            "2. high": "27.8900",
            "3. low": "27.6000",
            "4. close": "27.6400",
            "5. volume": "2821300"
        },
        "2025-10-23": {
            "1. open": "27.9200",
            "2. high": "27.9500",
            "3. low": "27.5700",
            "4. close": "27.8200",
            "5. volume": "3128526"
        },
        "2025-10-22": {
            "1. open": "27.4800",
            "2. high": "27.9600",
            "3. low": "27.4000",
            "4. close": "27.8900",
            "5. volume": "5473888"
        },
        "2025-10-21": {
            "1. open": "27.4500",
            "2. high": "27.5100",
            "3. low": "27.3200",
            "4. close": "27.4800",
            "5. volume": "2981067"
        },
        "2025-10-20": {
            "1. open": "27.5600",
            "2. high": "27.7000",
            "3. low": "27.3000",
            "4. close": "27.4700",
            "5. volume": "4514290"
        },
        "2025-10-17": {
            "1. open": "27.4300",
            "2. high": "27.7000",
            "3. low": "27.2300",
            "4. close": "27.4400",
            "5. volume": "4956735"
        },
        "2025-10-16": {
            "1. open": "27.2500",
            "2. high": "27.5000",
            "3. low": "27.2300",
            "4. close": "27.4300",
            "5. volume": "4874602"
        },
        "2025-10-15": {
            "1. open": "27.2300",
            "2. high": "27.4200",
            "3. low": "27.1300",
            "4. close": "27.4000",
            "5. volume": "4104676"
        },
        "2025-10-14": {
            "1. open": "26.9200",
            "2. high": "27.3700",
            "3. low": "26.9200",
            "4. close": "27.2300",
            "5. volume": "5889413"
        },
        "2025-10-13": {
            "1. open": "26.9500",
            "2. high": "26.9800",
            "3. low": "26.7600",
            "4. close": "26.9200",
            "5. volume": "5097393"
        },
        "2025-10-10": {
            "1. open": "27.1500",
            "2. high": "27.3600",
            "3. low": "27.0900",
            "4. close": "27.2600",
            "5. volume": "4165116"
        },
        "2025-10-09": {
            "1. open": "27.4400",
            "2. high": "27.5100",
            "3. low": "26.9700",
            "4. close": "27.1900",
            "5. volume": "6723419"
        },
        "2025-09-30": {
            "1. open": "27.3100",
            "2. high": "27.5900",
            "3. low": "27.3100",
            "4. close": "27.4300",
            "5. volume": "3873949"
        },
        "2025-09-29": {
            "1. open": "27.6000",
            "2. high": "27.6900",
            "3. low": "27.1000",
            "4. close": "27.4300",
            "5. volume": "6398432"
        },
        "2025-09-26": {
            "1. open": "27.7000",
            "2. high": "27.8500",
            "3. low": "27.4000",
            "4. close": "27.6000",
            "5. volume": "4653881"
        },
        "2025-09-25": {
            "1. open": "27.9800",
            "2. high": "28.2000",
            "3. low": "27.7000",
            "4. close": "27.8900",
            "5. volume": "4281080"
        },
        "2025-09-24": {
            "1. open": "27.7800",
            "2. high": "28.0300",
            "3. low": "27.6600",
            "4. close": "27.9700",
            "5. volume": "3427980"
        },
        "2025-09-23": {
            "1. open": "28.1100",
            "2. high": "28.1400",
            "3. low": "27.3600",
            "4. close": "27.8500",
            "5. volume": "7051039"
        },
        "2025-09-22": {
            "1. open": "28.8800",
            "2. high": "28.8800",
            "3. low": "28.0300",
            "4. close": "28.1500",
            "5. volume": "8686200"
        },
        "2025-09-19": {
            "1. open": "28.7800",
            "2. high": "28.9600",
            "3. low": "28.5100",
            "4. close": "28.9000",
            "5. volume": "5376600"
        },
        "2025-09-18": {
            "1. open": "29.4200",
            "2. high": "29.4800",
            "3. low": "28.6300",
            "4. close": "28.8000",
            "5. volume": "7568075"
        },
        "2025-09-17": {
            "1. open": "29.5500",
            "2. high": "29.8200",
            "3. low": "29.3100",
            "4. close": "29.4200",
            "5. volume": "5652706"
        },
        "2025-09-16": {
            "1. open": "29.8100",
            "2. high": "29.8200",
            "3. low": "29.4200",
            "4. close": "29.5500",
            "5. volume": "4455837"
        },
        "2025-09-15": {
            "1. open": "30.1200",
            "2. high": "30.1900",
            "3. low": "29.6300",
            "4. close": "29.8000",
            "5. volume": "5523809"
        },
        "2025-09-12": {
            "1. open": "30.5500",
            "2. high": "30.6300",
            "3. low": "30.0700",
            "4. close": "30.1000",
            "5. volume": "4612645"
        },
        "2025-09-11": {
            "1. open": "30.3500",
            "2. high": "30.5500",
            "3. low": "29.9600",
            "4. close": "30.5400",
            "5. volume": "5060761"
        },
        "2025-09-10": {
            "1. open": "30.6500",
            "2. high": "30.8100",
            "3. low": "30.3800",
            "4. close": "30.4500",
            "5. volume": "3484793"
        },
        "2025-09-09": {
            "1. open": "30.8700",
            "2. high": "30.9600",
            "3. low": "30.3800",
            "4. close": "30.6800",
            "5. volume": "4753621"
        },
        "2025-09-08": {
            "1. open": "30.6500",
            "2. high": "30.9700",
            "3. low": "30.6100",
            "4. close": "30.9700",
            "5. volume": "3844239"
        },
        "2025-09-05": {
            "1. open": "30.4200",
            "2. high": "30.8200",
            "3. low": "29.6200",
            "4. close": "30.7500",
            "5. volume": "6105716"
        },
        "2025-09-04": {
            "1. open": "30.0400",
            "2. high": "30.3100",
            "3. low": "29.7600",
            "4. close": "30.2600",
            "5. volume": "4003315"
        },
        "2025-09-03": {
            "1. open": "30.5300",
            "2. high": "30.8200",
            "3. low": "30.0200",
            "4. close": "30.0300",
            "5. volume": "4539279"
        },
        "2025-09-02": {
            "1. open": "30.9300",
            "2. high": "31.4600",
            "3. low": "30.1000",
            "4. close": "30.5400",
            "5. volume": "5005435"
        },
        "2025-09-01": {
            "1. open": "30.4800",
            "2. high": "30.9800",
            "3. low": "30.2500",
            "4. close": "30.8600",
            "5. volume": "5665268"
        },
        "2025-08-29": {
            "1. open": "30.4800",
            "2. high": "30.7900",
            "3. low": "30.3300",
            "4. close": "30.4600",
            "5. volume": "5740233"
        },
        "2025-08-28": {
            "1. open": "31.3500",
            "2. high": "31.4600",
            "3. low": "30.2300",
            "4. close": "30.5400",
            "5. volume": "9963922"
        },
        "2025-08-27": {
            "1. open": "31.8000",
            "2. high": "32.1000",
            "3. low": "31.4100",
            "4. close": "31.4200",
            "5. volume": "6451442"
        },
        "2025-08-26": {
            "1. open": "32.3000",
            "2. high": "32.5400",
            "3. low": "31.7100",
            "4. close": "31.7100",
            "5. volume": "12568531"
        },
        "2025-08-25": {
            "1. open": "31.9500",
            "2. high": "32.4200",
            "3. low": "31.5900",
            "4. close": "32.3800",
            "5. volume": "6350754"
        },
        "2025-08-22": {
            "1. open": "31.5000",
            "2. high": "31.8600",
            "3. low": "31.3600",
            "4. close": "31.8500",
            "5. volume": "4617937"
        },
        "2025-08-21": {
            "1. open": "31.4000",
            "2. high": "31.7800",
            "3. low": "31.3700",
            "4. close": "31.5100",
            "5. volume": "4815793"
        },
        "2025-08-20": {
            "1. open": "31.0000",
            "2. high": "31.3500",
            "3. low": "30.8500",
            "4. close": "31.3500",
            "5. volume": "5070645"
        },
        "2025-08-19": {
            "1. open": "31.1000",
            "2. high": "31.2000",
            "3. low": "30.8000",
            "4. close": "31.0800",
            "5. volume": "3997812"
        },
        "2025-08-18": {
            "1. open": "31.2000",
            "2. high": "31.3000",
            "3. low": "30.9000",
            "4. close": "31.0600",
            "5. volume": "4949207"
        },
        "2025-08-15": {
            "1. open": "30.9400",
            "2. high": "31.1400",
            "3. low": "30.7800",
            "4. close": "31.1400",
            "5. volume": "3836360"
        },
        "2025-08-14": {
            "1. open": "31.5000",
            "2. high": "31.5700",
            "3. low": "30.9900",
            "4. close": "31.0000",
            "5. volume": "3249736"
        },
        "2025-08-13": {
            "1. open": "31.8800",
            "2. high": "32.3000",
            "3. low": "31.4100",
            "4. close": "31.5000",
            "5. volume": "4565442"
        },
        "2025-08-12": {
            "1. open": "31.4000",
            "2. high": "31.9700",
            "3. low": "31.2200",
            "4. close": "31.8800",
            "5. volume": "3443283"
        },
        "2025-08-11": {
            "1. open": "31.2300",
            "2. high": "31.7400",
            "3. low": "31.0500",
            "4. close": "31.4000",
            "5. volume": "4271197"
        },
        "2025-08-08": {
            "1. open": "31.6000",
            "2. high": "31.6200",
            "3. low": "31.1800",
            "4. close": "31.2500",
            "5. volume": "2869937"
        },
        "2025-08-07": {
            "1. open": "31.7900",
            "2. high": "32.1000",
            "3. low": "31.4100",
            "4. close": "31.5800",
            "5. volume": "2789759"
        },
        "2025-08-06": {
            "1. open": "32.1700",
            "2. high": "32.1700",
            "3. low": "31.6700",
            "4. close": "31.8700",
            "5. volume": "3521830"
        },
        "2025-08-05": {
            "1. open": "31.6200",
            "2. high": "32.6500",
            "3. low": "31.6200",
            "4. close": "32.2300",
            "5. volume": "7400069"
        },
        "2025-08-04": {
            "1. open": "31.3000",
            "2. high": "31.6800",
            "3. low": "30.6000",
            "4. close": "31.2000",
            "5. volume": "4622844"
        },
        "2025-08-01": {
            "1. open": "30.7400",
            "2. high": "31.3800",
            "3. low": "30.6600",
            "4. close": "31.1700",
            "5. volume": "4523897"
        },
        "2025-07-31": {
            "1. open": "30.5000",
            "2. high": "31.4000",
            "3. low": "30.3000",
            "4. close": "30.8300",
            "5. volume": "7414066"
        },
        "2025-07-30": {
            "1. open": "31.2700",
            "2. high": "31.2700",
            "3. low": "30.2100",
            "4. close": "30.4400",
            "5. volume": "7740672"
        },
        "2025-07-29": {
            "1. open": "31.1400",
            "2. high": "31.9700",
            "3. low": "30.9700",
            "4. close": "31.2700",
            "5. volume": "5016975"
        },
        "2025-07-28": {
            "1. open": "31.4300",
            "2. high": "31.5000",
            "3. low": "31.0400",
            "4. close": "31.0700",
            "5. volume": "3649174"
        },
        "2025-07-25": {
            "1. open": "31.1200",
            "2. high": "31.5500",
            "3. low": "30.7600",
            "4. close": "31.4100",
            "5. volume": "6275195"
        },
        "2025-07-24": {
            "1. open": "30.6000",
            "2. high": "31.2300",
            "3. low": "30.4600",
            "4. close": "31.0000",
            "5. volume": "4125232"
        },
        "2025-07-23": {
            "1. open": "30.9200",
            "2. high": "31.0000",
            "3. low": "30.3700",
            "4. close": "30.6100",
            "5. volume": "4441495"
        },
        "2025-07-22": {
            "1. open": "29.9100",
            "2. high": "31.1100",
            "3. low": "29.7800",
            "4. close": "30.9000",
            "5. volume": "8841033"
        },
        "2025-07-21": {
            "1. open": "29.5700",
            "2. high": "29.9400",
            "3. low": "29.4200",
            "4. close": "29.9100",
            "5. volume": "5644139"
        },
        "2025-07-18": {
            "1. open": "29.3600",
            "2. high": "29.5800",
            "3. low": "29.2700",
            "4. close": "29.4500",
            "5. volume": "3756549"
        },
        "2025-07-17": {
            "1. open": "29.1900",
            "2. high": "29.5900",
            "3. low": "29.1800",
            "4. close": "29.3500",
            "5. volume": "3207519"
        },
        "2025-07-16": {
            "1. open": "29.2300",
            "2. high": "29.6200",
            "3. low": "29.2200",
            "4. close": "29.3200",
            "5. volume": "4029489"
        },
        "2025-07-15": {
            "1. open": "29.2100",
            "2. high": "29.4100",
            "3. low": "28.9900",
            "4. close": "29.2300",
            "5. volume": "5533367"
        },
        "2025-07-14": {
            "1. open": "29.6700",
            "2. high": "29.7000",
            "3. low": "29.1600",
            "4. close": "29.3100",
            "5. volume": "4804668"
        },
        "2025-07-11": {
            "1. open": "29.7300",
            "2. high": "29.8000",
            "3. low": "29.5700",
            "4. close": "29.6600",
            "5. volume": "3501044"
        },
        "2025-07-10": {
            "1. open": "29.7800",
            "2. high": "29.8900",
            "3. low": "29.5600",
            "4. close": "29.7300",
            "5. volume": "3594928"
        },
        "2025-07-09": {
            "1. open": "29.5600",
            "2. high": "30.2400",
            "3. low": "29.5300",
            "4. close": "29.8400",
            "5. volume": "5858518"
        },
        "2025-07-08": {
            "1. open": "29.6200",
            "2. high": "29.8800",
            "3. low": "29.5000",
            "4. close": "29.5300",
            "5. volume": "5308050"
        },
        "2025-07-07": {
            "1. open": "29.1100",
            "2. high": "29.7500",
            "3. low": "29.0000",
            "4. close": "29.6200",
            "5. volume": "6546930"
        },
        "2025-07-04": {
            "1. open": "29.0800",
            "2. high": "29.3300",
            "3. low": "28.9500",
            "4. close": "29.0700",
            "5. volume": "4729446"
        },
        "2025-07-03": {
            "1. open": "28.9500",
            "2. high": "29.3000",
            "3. low": "28.8200",
            "4. close": "29.1300",
            "5. volume": "4601375"
        },
        "2025-07-02": {
            "1. open": "29.4400",
            "2. high": "29.4500",
            "3. low": "28.9400",
            "4. close": "29.0400",
            "5. volume": "5139218"
        },
        "2025-07-01": {
            "1. open": "29.0900",
            "2. high": "29.4200",
            "3. low": "28.8300",
            "4. close": "29.3500",
            "5. volume": "7804258"
        },
        "2025-06-30": {
            "1. open": "28.6300",
            "2. high": "29.0200",
            "3. low": "28.5500",
            "4. close": "28.9900",
            "5. volume": "6897850"
        },
        "2025-06-27": {
            "1. open": "28.5000",
            "2. high": "28.7900",
            "3. low": "28.4000",
            "4. close": "28.6300",
            "5. volume": "7693408"
        },
        "2025-06-26": {
            "1. open": "29.1200",
            "2. high": "29.1300",
            "3. low": "28.1800",
            "4. close": "28.6300",
            "5. volume": "24152568"
        },
        "2025-06-25": {
            "1. open": "29.8600",
            "2. high": "30.0400",
            "3. low": "29.6200",
            "4. close": "29.8400",
            "5. volume": "6587789"
        },
        "2025-06-24": {
            "1. open": "30.0200",
            "2. high": "30.3700",
            "3. low": "29.6500",
            "4. close": "29.8600",
            "5. volume": "8247964"
        },
        "2025-06-23": {
            "1. open": "29.7600",
            "2. high": "30.1200",
            "3. low": "29.5000",
            "4. close": "29.8200",
            "5. volume": "5355049"
        },
        "2025-06-20": {
            "1. open": "30.8300",
            "2. high": "30.9200",
            "3. low": "29.7100",
            "4. close": "29.9300",
            "5. volume": "9955972"
        },
        "2025-06-19": {
            "1. open": "31.5400",
            "2. high": "31.7100",
            "3. low": "30.6000",
            "4. close": "30.8300",
            "5. volume": "7707011"
        },
        "2025-06-18": {
            "1. open": "32.8900",
            "2. high": "32.9100",
            "3. low": "31.5000",
            "4. close": "31.6500",
            "5. volume": "8069296"
        },
        "2025-06-17": {
            "1. open": "33.8100",
            "2. high": "34.6900",
            "3. low": "32.5000",
            "4. close": "32.6800",
            "5. volume": "8741971"
        },
        "2025-06-16": {
            "1. open": "32.9000",
            "2. high": "34.0400",
            "3. low": "32.8500",
            "4. close": "33.8700",
            "5. volume": "9593037"
        },
        "2025-06-13": {
            "1. open": "34.5800",
            "2. high": "34.7500",
            "3. low": "32.9000",
            "4. close": "33.1600",
            "5. volume": "11625162"
        },
        "2025-06-12": {
            "1. open": "35.1600",
            "2. high": "36.0000",
            "3. low": "34.5100",
            "4. close": "34.5800",
            "5. volume": "9368460"
        },
        "2025-06-11": {
            "1. open": "35.0000",
            "2. high": "35.3000",
            "3. low": "34.4200",
            "4. close": "35.0700",
            "5. volume": "10018961"
        },
        "2025-06-10": {
            "1. open": "34.7500",
            "2. high": "35.9900",
            "3. low": "34.3600",
            "4. close": "34.9000",
            "5. volume": "17610370"
        },
        "2025-06-09": {
            "1. open": "31.6900",
            "2. high": "34.6800",
            "3. low": "31.4900",
            "4. close": "34.3500",
            "5. volume": "18798524"
        },
        "2025-06-06": {
            "1. open": "31.7500",
            "2. high": "31.8500",
            "3. low": "31.0800",
            "4. close": "31.5300",
            "5. volume": "6880845"
        },
        "2025-06-05": {
            "1. open": "30.6600",
            "2. high": "32.4000",
            "3. low": "30.6300",
            "4. close": "31.7600",
            "5. volume": "12333259"
        },
        "2025-06-04": {
            "1. open": "30.7000",
            "2. high": "30.9500",
            "3. low": "30.5000",
            "4. close": "30.6400",
            "5. volume": "4640764"
        },
        "2025-06-03": {
            "1. open": "29.3600",
            "2. high": "31.0900",
            "3. low": "29.2800",
            "4. close": "30.7100",
            "5. volume": "7854998"
        },
        "2025-05-30": {
            "1. open": "29.4900",
            "2. high": "29.8800",
            "3. low": "29.2800",
            "4. close": "29.5100",
            "5. volume": "3499201"
        },
        "2025-05-29": {
            "1. open": "29.4100",
            "2. high": "29.7800",
            "3. low": "29.0000",
            "4. close": "29.4800",
            "5. volume": "5038600"
        },
        "2025-05-28": {
            "1. open": "28.7100",
            "2. high": "29.6600",
            "3. low": "28.6000",
            "4. close": "29.5700",
            "5. volume": "7053214"
        },
        "2025-05-27": {
            "1. open": "28.2100",
            "2. high": "28.9600",
            "3. low": "28.0300",
            "4. close": "28.7000",
            "5. volume": "4180811"
        },
        "2025-05-26": {
            "1. open": "27.8300",
            "2. high": "28.3700",
            "3. low": "27.6000",
            "4. close": "28.2100",
            "5. volume": "3493778"
        },
        "2025-05-23": {
            "1. open": "28.2000",
            "2. high": "28.3300",
            "3. low": "27.6900",
            "4. close": "27.7000",
            "5. volume": "2935800"
        },
        "2025-05-22": {
            "1. open": "28.5200",
            "2. high": "28.5800",
            "3. low": "28.1200",
            "4. close": "28.2300",
            "5. volume": "2986942"
        },
        "2025-05-21": {
            "1. open": "28.7000",
            "2. high": "28.9400",
            "3. low": "28.3300",
            "4. close": "28.6300",
            "5. volume": "3922400"
        },
        "2025-05-20": {
            "1. open": "27.8200",
            "2. high": "29.0600",
            "3. low": "27.8100",
            "4. close": "28.7400",
            "5. volume": "7068684"
        },
        "2025-05-19": {
            "1. open": "28.3500",
            "2. high": "28.3800",
            "3. low": "27.5000",
            "4. close": "27.8300",
            "5. volume": "4740048"
        },
        "2025-05-16": {
            "1. open": "29.5000",
            "2. high": "29.5000",
            "3. low": "29.0500",
            "4. close": "29.1600",
            "5. volume": "4669400"
        },
        "2025-05-15": {
            "1. open": "29.9000",
            "2. high": "30.2500",
            "3. low": "29.3700",
            "4. close": "29.3900",
            "5. volume": "5046829"
        },
        "2025-05-14": {
            "1. open": "29.7300",
            "2. high": "30.0500",
            "3. low": "29.5300",
            "4. close": "29.9100",
            "5. volume": "3631241"
        },
        "2025-05-13": {
            "1. open": "30.0100",
            "2. high": "30.1500",
            "3. low": "29.7100",
            "4. close": "29.8300",
            "5. volume": "4178337"
        },
        "2025-05-12": {
            "1. open": "30.0600",
            "2. high": "30.2100",
            "3. low": "29.5800",
            "4. close": "29.7100",
            "5. volume": "3938912"
        },
        "2025-05-09": {
            "1. open": "30.1300",
            "2. high": "30.2800",
            "3. low": "29.8100",
            "4. close": "30.0500",
            "5. volume": "2001812"
        },
        "2025-05-08": {
            "1. open": "30.1100",
            "2. high": "30.3300",
            "3. low": "30.0100",
            "4. close": "30.1200",
            "5. volume": "2596401"
        },
        "2025-05-07": {
            "1. open": "31.0000",
            "2. high": "31.1400",
            "3. low": "30.0000",
            "4. close": "30.2500",
            "5. volume": "4041357"
        },
        "2025-05-06": {
            "1. open": "29.6000",
            "2. high": "30.9600",
            "3. low": "29.2900",
            "4. close": "30.8200",
            "5. volume": "6594897"
        },
        "2025-04-30": {
            "1. open": "29.4700",
            "2. high": "30.0500",
            "3. low": "29.3900",
            "4. close": "29.4200",
            "5. volume": "5086997"
        },
        "2025-04-29": {
            "1. open": "30.5800",
            "2. high": "30.5800",
            "3. low": "28.9500",
            "4. close": "29.4700",
            "5. volume": "12970727"
        },
        "2025-04-28": {
            "1. open": "31.2200",
            "2. high": "31.9100",
            "3. low": "31.1300",
            "4. close": "31.3200",
            "5. volume": "5305736"
        },
        "2025-04-25": {
            "1. open": "32.0000",
            "2. high": "32.1800",
            "3. low": "31.2200",
            "4. close": "31.2200",
            "5. volume": "3943136"
        },
        "2025-04-24": {
            "1. open": "31.1700",
            "2. high": "32.0500",
            "3. low": "31.0600",
            "4. close": "31.5500",
            "5. volume": "6963552"
        },
        "2025-04-23": {
            "1. open": "31.6900",
            "2. high": "31.6900",
            "3. low": "30.9000",
            "4. close": "31.1700",
            "5. volume": "4632862"
        },
        "2025-04-22": {
            "1. open": "31.5900",
            "2. high": "31.8400",
            "3. low": "31.0300",
            "4. close": "31.4100",
            "5. volume": "5361600"
        },
        "2025-04-21": {
            "1. open": "29.9800",
            "2. high": "31.8400",
            "3. low": "29.5100",
            "4. close": "31.6000",
            "5. volume": "10342106"
        },
        "2025-04-18": {
            "1. open": "29.5800",
            "2. high": "30.1600",
            "3. low": "29.5800",
            "4. close": "30.0100",
            "5. volume": "3431994"
        },
        "2025-04-17": {
            "1. open": "29.5800",
            "2. high": "29.9800",
            "3. low": "29.3200",
            "4. close": "29.6500",
            "5. volume": "6097083"
        },
        "2025-04-16": {
            "1. open": "30.5900",
            "2. high": "30.7000",
            "3. low": "29.2900",
            "4. close": "29.8700",
            "5. volume": "5706038"
        },
        "2025-04-15": {
            "1. open": "30.5500",
            "2. high": "31.1800",
            "3. low": "30.2500",
            "4. close": "30.5900",
            "5. volume": "5695590"
        },
        "2025-04-14": {
            "1. open": "30.3900",
            "2. high": "31.1500",
            "3. low": "30.3900",
            "4. close": "30.5500",
            "5. volume": "4228698"
        },
        "2025-04-11": {
            "1. open": "30.5800",
            "2. high": "31.0300",
            "3. low": "30.0800",
            "4. close": "30.3500",
            "5. volume": "5164407"
        },
        "2025-04-10": {
            "1. open": "30.4100",
            "2. high": "31.2400",
            "3. low": "30.0000",
            "4. close": "30.8500",
            "5. volume": "6174600"
        },
        "2025-04-09": {
            "1. open": "29.3100",
            "2. high": "30.3700",
            "3. low": "28.7200",
            "4. close": "29.9300",
            "5. volume": "6020813"
        },
        "2025-04-08": {
            "1. open": "28.5200",
            "2. high": "29.8000",
            "3. low": "28.5200",
            "4. close": "29.5600",
            "5. volume": "9026469"
        },
        "2025-04-07": {
            "1. open": "29.5000",
            "2. high": "30.4500",
            "3. low": "28.4400",
            "4. close": "28.4400",
            "5. volume": "12469335"
        },
        "2025-04-03": {
            "1. open": "31.5000",
            "2. high": "32.2000",
            "3. low": "31.2200",
            "4. close": "31.6000",
            "5. volume": "7364562"
        },
        "2025-04-02": {
            "1. open": "32.5000",
            "2. high": "33.0800",
            "3. low": "31.4900",
            "4. close": "31.6400",
            "5. volume": "9990425"
        },
        "2025-04-01": {
            "1. open": "30.5900",
            "2. high": "32.4100",
            "3. low": "30.5800",
            "4. close": "31.8100",
            "5. volume": "11303701"
        },
        "2025-03-31": {
            "1. open": "30.6100",
            "2. high": "31.3400",
            "3. low": "30.2600",
            "4. close": "30.5900",
            "5. volume": "5042758"
        },
        "2025-03-28": {
            "1. open": "30.8300",
            "2. high": "31.0800",
            "3. low": "30.3200",
            "4. close": "30.6800",
            "5. volume": "5969464"
        },
        "2025-03-27": {
            "1. open": "30.0900",
            "2. high": "31.2000",
            "3. low": "29.8200",
            "4. close": "31.0400",
            "5. volume": "10739980"
        },
        "2025-03-26": {
            "1. open": "29.3000",
            "2. high": "30.3000",
            "3. low": "28.9200",
            "4. close": "30.1300",
            "5. volume": "10425730"
        },
        "2025-03-25": {
            "1. open": "29.1400",
            "2. high": "29.2500",
            "3. low": "28.8500",
            "4. close": "29.2100",
            "5. volume": "3256203"
        },
        "2025-03-24": {
            "1. open": "29.2600",
            "2. high": "29.5900",
            "3. low": "28.8000",
            "4. close": "29.0400",
            "5. volume": "3571969"
        },
        "2025-03-21": {
            "1. open": "29.2600",
            "2. high": "30.2600",
            "3. low": "29.2000",
            "4. close": "29.3300",
            "5. volume": "5731872"
        },
        "2025-03-20": {
            "1. open": "29.6300",
            "2. high": "29.7400",
            "3. low": "29.1700",
            "4. close": "29.2100",
            "5. volume": "4299102"
        },
        "2025-03-19": {
            "1. open": "30.0000",
            "2. high": "30.2900",
            "3. low": "29.4400",
            "4. close": "29.6300",
            "5. volume": "4801554"
        },
        "2025-03-18": {
            "1. open": "30.2900",
            "2. high": "30.3500",
            "3. low": "29.6800",
            "4. close": "30.1200",
            "5. volume": "5963551"
        },
        "2025-03-17": {
            "1. open": "30.7000",
            "2. high": "30.8800",
            "3. low": "30.0200",
            "4. close": "30.1500",
            "5. volume": "8483372"
        },
        "2025-03-14": {
            "1. open": "29.7200",
            "2. high": "30.7600",
            "3. low": "29.7200",
            "4. close": "30.6300",
            "5. volume": "13885816"
        },
        "2025-03-13": {
            "1. open": "29.7600",
            "2. high": "30.7000",
            "3. low": "29.6200",
            "4. close": "29.7100",
            "5. volume": "12563693"
        },
        "2025-03-12": {
            "1. open": "28.7500",
            "2. high": "30.1000",
            "3. low": "28.4600",
            "4. close": "29.7700",
            "5. volume": "16471089"
        },
        "2025-03-11": {
            "1. open": "27.5800",
            "2. high": "28.6000",
            "3. low": "27.4600",
            "4. close": "28.6000",
            "5. volume": "6476526"
        },
        "2025-03-10": {
            "1. open": "27.8500",
            "2. high": "27.9400",
            "3. low": "27.6400",
            "4. close": "27.8100",
            "5. volume": "3413344"
        },
        "2025-03-07": {
            "1. open": "27.7000",
            "2. high": "27.9400",
            "3. low": "27.5200",
            "4. close": "27.8500",
            "5. volume": "3728497"
        },
        "2025-03-06": {
            "1. open": "27.3700",
            "2. high": "28.0100",
            "3. low": "27.3000",
            "4. close": "27.7800",
            "5. volume": "5727769"
        },
        "2025-03-05": {
            "1. open": "27.4400",
            "2. high": "27.4900",
            "3. low": "27.0500",
            "4. close": "27.2900",
            "5. volume": "4422301"
        },
        "2025-03-04": {
            "1. open": "27.4700",
            "2. high": "27.5200",
            "3. low": "27.1700",
            "4. close": "27.4000",
            "5. volume": "3666019"
        },
        "2025-03-03": {
            "1. open": "27.6200",
            "2. high": "28.0500",
            "3. low": "27.4200",
            "4. close": "27.5300",
            "5. volume": "5120856"
        },
        "2025-02-28": {
            "1. open": "28.0100",
            "2. high": "28.6300",
            "3. low": "27.5700",
            "4. close": "27.6100",
            "5. volume": "7315597"
        },
        "2025-02-27": {
            "1. open": "27.3900",
            "2. high": "28.0500",
            "3. low": "27.2100",
            "4. close": "27.9700",
            "5. volume": "8424723"
        },
        "2025-02-26": {
            "1. open": "27.0200",
            "2. high": "27.3900",
            "3. low": "27.0200",
            "4. close": "27.3400",
            "5. volume": "4711475"
        },
        "2025-02-25": {
            "1. open": "27.5300",
            "2. high": "27.5600",
            "3. low": "27.0400",
            "4. close": "27.0800",
            "5. volume": "7441966"
        },
        "2025-02-24": {
            "1. open": "27.7000",
            "2. high": "27.8300",
            "3. low": "27.5200",
            "4. close": "27.7000",
            "5. volume": "5440463"
        },
        "2025-02-21": {
            "1. open": "28.1500",
            "2. high": "28.2700",
            "3. low": "27.5200",
            "4. close": "27.8000",
            "5. volume": "8092038"
        },
        "2025-02-20": {
            "1. open": "27.8000",
            "2. high": "28.2800",
            "3. low": "27.7000",
            "4. close": "28.0900",
            "5. volume": "5151602"
        },
        "2025-02-19": {
            "1. open": "27.9600",
            "2. high": "28.0900",
            "3. low": "27.6100",
            "4. close": "27.8800",
            "5. volume": "6969742"
        },
        "2025-02-18": {
            "1. open": "28.7000",
            "2. high": "28.7200",
            "3. low": "27.9000",
            "4. close": "27.9900",
            "5. volume": "5904549"
        },
        "2025-02-17": {
            "1. open": "29.3200",
            "2. high": "29.4400",
            "3. low": "28.5600",
            "4. close": "28.7600",
            "5. volume": "6663846"
        },
        "2025-02-14": {
            "1. open": "28.7500",
            "2. high": "29.0800",
            "3. low": "28.7000",
            "4. close": "29.0800",
            "5. volume": "4704386"
        },
        "2025-02-13": {
            "1. open": "28.4700",
            "2. high": "29.0500",
            "3. low": "28.3400",
            "4. close": "28.7700",
            "5. volume": "6378952"
        },
        "2025-02-12": {
            "1. open": "28.2000",
            "2. high": "28.4600",
            "3. low": "28.1000",
            "4. close": "28.4600",
            "5. volume": "3931601"
        },
        "2025-02-11": {
            "1. open": "28.7100",
            "2. high": "28.7300",
            "3. low": "28.2200",
            "4. close": "28.3400",
            "5. volume": "3955900"
        },
        "2025-02-10": {
            "1. open": "28.4900",
            "2. high": "28.7800",
            "3. low": "28.2500",
            "4. close": "28.7200",
            "5. volume": "4393200"
        },
        "2025-02-07": {
            "1. open": "28.1800",
            "2. high": "28.6000",
            "3. low": "27.9500",
            "4. close": "28.4900",
            "5. volume": "5024521"
        },
        "2025-02-06": {
            "1. open": "27.8200",
            "2. high": "28.2500",
            "3. low": "27.6800",
            "4. close": "28.1800",
            "5. volume": "4092286"
        },
        "2025-02-05": {
            "1. open": "28.5800",
            "2. high": "28.6200",
            "3. low": "27.7400",
            "4. close": "27.8100",
            "5. volume": "5557489"
        },
        "2025-01-27": {
            "1. open": "28.4000",
            "2. high": "28.7000",
            "3. low": "28.3200",
            "4. close": "28.4000",
            "5. volume": "2773243"
        },
        "2025-01-24": {
            "1. open": "28.1100",
            "2. high": "28.4000",
            "3. low": "28.0800",
            "4. close": "28.3900",
            "5. volume": "2726991"
        },
        "2025-01-23": {
            "1. open": "28.3000",
            "2. high": "28.7100",
            "3. low": "28.1500",
            "4. close": "28.1500",
            "5. volume": "3360086"
        },
        "2025-01-22": {
            "1. open": "28.3600",
            "2. high": "28.4100",
            "3. low": "28.0600",
            "4. close": "28.2900",
            "5. volume": "3016224"
        },
        "2025-01-21": {
            "1. open": "28.6000",
            "2. high": "28.6800",
            "3. low": "28.1700",
            "4. close": "28.5800",
            "5. volume": "2635240"
        },
        "2025-01-20": {
            "1. open": "28.5500",
            "2. high": "28.8400",
            "3. low": "28.3700",
            "4. close": "28.4700",
            "5. volume": "3045700"
        },
        "2025-01-17": {
            "1. open": "28.3200",
            "2. high": "28.6200",
            "3. low": "28.2500",
            "4. close": "28.3900",
            "5. volume": "3117370"
        },
        "2025-01-16": {
            "1. open": "28.5000",
            "2. high": "28.8400",
            "3. low": "28.2500",
            "4. close": "28.4700",
            "5. volume": "3740479"
        },
        "2025-01-15": {
            "1. open": "28.7400",
            "2. high": "28.7900",
            "3. low": "28.2900",
            "4. close": "28.3500",
            "5. volume": "3727878"
        },
        "2025-01-14": {
            "1. open": "28.1900",
            "2. high": "28.8300",
            "3. low": "28.1000",
            "4. close": "28.7300",
            "5. volume": "4910697"
        },
        "2025-01-13": {
            "1. open": "27.5100",
            "2. high": "28.3000",
            "3. low": "27.4400",
            "4. close": "28.1900",
            "5. volume": "4775761"
        },
        "2025-01-10": {
            "1. open": "28.2500",
            "2. high": "28.3100",
            "3. low": "27.8500",
            "4. close": "27.8500",
            "5. volume": "4424316"
        },
        "2025-01-09": {
            "1. open": "28.2300",
            "2. high": "28.4800",
            "3. low": "28.0100",
            "4. close": "28.1200",
            "5. volume": "3813522"
        },
        "2025-01-08": {
            "1. open": "28.6400",
            "2. high": "28.6500",
            "3. low": "27.9400",
            "4. close": "28.4300",
            "5. volume": "4523623"
        },
        "2025-01-07": {
            "1. open": "28.7600",
            "2. high": "28.8800",
            "3. low": "28.2800",
            "4. close": "28.7200",
            "5. volume": "3807023"
        },
        "2025-01-06": {
            "1. open": "28.9100",
            "2. high": "29.1400",
            "3. low": "28.4700",
            "4. close": "28.7600",
            "5. volume": "3963846"
        },
        "2025-01-03": {
            "1. open": "29.5000",
            "2. high": "29.8400",
            "3. low": "28.7800",
            "4. close": "28.8700",
            "5. volume": "5757357"
        },
        "2025-01-02": {
            "1. open": "30.1900",
            "2. high": "30.5400",
            "3. low": "29.2000",
            "4. close": "29.4900",
            "5. volume": "6725041"
        },
        "2024-12-31": {
            "1. open": "30.2000",
            "2. high": "30.6500",
            "3. low": "29.9200",
            "4. close": "30.2500",
            "5. volume": "6750100"
        },
        "2024-12-30": {
            "1. open": "30.5500",
            "2. high": "30.8600",
            "3. low": "30.1500",
            "4. close": "30.2800",
            "5. volume": "4874041"
        },
        "2024-12-27": {
            "1. open": "30.4000",
            "2. high": "30.8500",
            "3. low": "30.1200",
            "4. close": "30.6000",
            "5. volume": "4951819"
        },
        "2024-12-26": {
            "1. open": "30.4500",
            "2. high": "30.5900",
            "3. low": "30.2400",
            "4. close": "30.3600",
            "5. volume": "4157891"
        },
        "2024-12-25": {
            "1. open": "31.0000",
            "2. high": "31.0700",
            "3. low": "30.3000",
            "4. close": "30.5500",
            "5. volume": "4828127"
        },
        "2024-12-24": {
            "1. open": "30.7200",
            "2. high": "31.1500",
            "3. low": "30.6300",
            "4. close": "31.0800",
            "5. volume": "5695897"
        },
        "2024-12-23": {
            "1. open": "31.8200",
            "2. high": "32.0900",
            "3. low": "30.8500",
            "4. close": "30.9600",
            "5. volume": "8080789"
        },
        "2024-12-20": {
            "1. open": "31.6000",
            "2. high": "32.7600",
            "3. low": "31.5400",
            "4. close": "32.0400",
            "5. volume": "7983347"
        },
        "2024-12-19": {
            "1. open": "31.9000",
            "2. high": "32.4400",
            "3. low": "31.6500",
            "4. close": "31.7100",
            "5. volume": "7578495"
        },
        "2024-12-18": {
            "1. open": "31.8700",
            "2. high": "32.6800",
            "3. low": "31.1900",
            "4. close": "32.3800",
            "5. volume": "10576024"
        },
        "2024-12-17": {
            "1. open": "31.5500",
            "2. high": "32.1100",
            "3. low": "31.2600",
            "4. close": "31.8700",
            "5. volume": "8662904"
        },
        "2024-12-16": {
            "1. open": "32.3200",
            "2. high": "32.9500",
            "3. low": "31.5200",
            "4. close": "31.8800",
            "5. volume": "15828881"
        },
        "2024-12-13": {
            "1. open": "33.0700",
            "2. high": "33.6800",
            "3. low": "32.5300",
            "4. close": "32.6500",
            "5. volume": "23707690"
        },
        "2024-12-12": {
            "1. open": "31.7500",
            "2. high": "33.7700",
            "3. low": "31.5500",
            "4. close": "33.2800",
            "5. volume": "19567885"
        },
        "2024-12-11": {
            "1. open": "30.9200",
            "2. high": "31.7600",
            "3. low": "30.8900",
            "4. close": "31.7400",
            "5. volume": "9967172"
        },
        "2024-12-10": {
            "1. open": "32.0000",
            "2. high": "32.6000",
            "3. low": "30.9800",
            "4. close": "31.0600",
            "5. volume": "14677779"
        },
        "2024-12-09": {
            "1. open": "31.3100",
            "2. high": "31.5900",
            "3. low": "30.8400",
            "4. close": "30.9000",
            "5. volume": "8136334"
        },
        "2024-12-06": {
            "1. open": "31.3500",
            "2. high": "31.5900",
            "3. low": "30.9300",
            "4. close": "31.5000",
            "5. volume": "8930833"
        },
        "2024-12-05": {
            "1. open": "31.0100",
            "2. high": "31.3200",
            "3. low": "30.7800",
            "4. close": "31.3000",
            "5. volume": "10649963"
        },
        "2024-12-04": {
            "1. open": "31.7800",
            "2. high": "32.0800",
            "3. low": "30.9300",
            "4. close": "31.3200",
            "5. volume": "12111612"
        },
        "2024-12-03": {
            "1. open": "32.9600",
            "2. high": "32.9600",
            "3. low": "31.8400",
            "4. close": "32.1500",
            "5. volume": "13300053"
        },
        "2024-12-02": {
            "1. open": "33.2000",
            "2. high": "33.2700",
            "3. low": "32.2000",
            "4. close": "32.8300",
            "5. volume": "15537885"
        },
        "2024-11-29": {
            "1. open": "32.8800",
            "2. high": "33.7600",
            "3. low": "32.6800",
            "4. close": "33.2800",
            "5. volume": "15705746"
        },
        "2024-11-28": {
            "1. open": "34.0100",
            "2. high": "35.3700",
            "3. low": "33.0100",
            "4. close": "33.2900",
            "5. volume": "27876146"
        },
        "2024-11-27": {
            "1. open": "31.5000",
            "2. high": "35.1000",
            "3. low": "31.0500",
            "4. close": "34.4000",
            "5. volume": "34847045"
        },
        "2024-11-26": {
            "1. open": "30.9000",
            "2. high": "32.6700",
            "3. low": "30.4000",
            "4. close": "32.6700",
            "5. volume": "29453992"
        },
        "2024-11-25": {
            "1. open": "29.2700",
            "2. high": "30.0500",
            "3. low": "29.1100",
            "4. close": "29.7000",
            "5. volume": "4175403"
        },
        "2024-11-22": {
            "1. open": "30.4100",
            "2. high": "30.4400",
            "3. low": "29.2000",
            "4. close": "29.2700",
            "5. volume": "4103035"
        },
        "2024-11-21": {
            "1. open": "30.3900",
            "2. high": "30.7700",
            "3. low": "30.2000",
            "4. close": "30.4100",
            "5. volume": "2809634"
        },
        "2024-11-20": {
            "1. open": "30.0000",
            "2. high": "30.7000",
            "3. low": "29.8700",
            "4. close": "30.5700",
            "5. volume": "4451938"
        },
        "2024-11-19": {
            "1. open": "29.8600",
            "2. high": "30.2300",
            "3. low": "29.5600",
            "4. close": "30.1500",
            "5. volume": "4788444"
        },
        "2024-11-18": {
            "1. open": "30.0800",
            "2. high": "30.4000",
            "3. low": "29.5600",
            "4. close": "29.7300",
            "5. volume": "4283409"
        },
        "2024-11-15": {
            "1. open": "30.7300",
            "2. high": "31.0300",
            "3. low": "30.2100",
            "4. close": "30.2100",
            "5. volume": "5177770"
        },
        "2024-11-14": {
            "1. open": "31.2800",
            "2. high": "31.6500",
            "3. low": "30.7900",
            "4. close": "30.7900",
            "5. volume": "5912854"
        },
        "2024-11-13": {
            "1. open": "31.1400",
            "2. high": "31.4800",
            "3. low": "30.7600",
            "4. close": "31.4300",
            "5. volume": "6601491"
        },
        "2024-11-12": {
            "1. open": "31.0600",
            "2. high": "31.8000",
            "3. low": "31.0200",
            "4. close": "31.3600",
            "5. volume": "6877874"
        },
        "2024-11-11": {
            "1. open": "31.0000",
            "2. high": "31.2200",
            "3. low": "30.3600",
            "4. close": "31.1600",
            "5. volume": "6455522"
        },
        "2024-11-08": {
            "1. open": "31.9100",
            "2. high": "32.2000",
            "3. low": "31.0000",
            "4. close": "31.4500",
            "5. volume": "6598694"
        },
        "2024-11-07": {
            "1. open": "30.1200",
            "2. high": "31.6800",
            "3. low": "30.1000",
            "4. close": "31.6300",
            "5. volume": "7825919"
        },
        "2024-11-06": {
            "1. open": "30.5000",
            "2. high": "30.9400",
            "3. low": "30.1000",
            "4. close": "30.5300",
            "5. volume": "6322441"
        },
        "2024-11-05": {
            "1. open": "29.5100",
            "2. high": "30.7500",
            "3. low": "29.3600",
            "4. close": "30.6600",
            "5. volume": "8066950"
        },
        "2024-11-04": {
            "1. open": "29.0000",
            "2. high": "29.6500",
            "3. low": "29.0000",
            "4. close": "29.5400",
            "5. volume": "4537532"
        },
        "2024-11-01": {
            "1. open": "28.9900",
            "2. high": "29.4200",
            "3. low": "28.7800",
            "4. close": "29.0300",
            "5. volume": "5224556"
        },
        "2024-10-31": {
            "1. open": "29.0000",
            "2. high": "29.3500",
            "3. low": "28.8700",
            "4. close": "29.0000",
            "5. volume": "6277593"
        },
        "2024-10-30": {
            "1. open": "29.9100",
            "2. high": "29.9600",
            "3. low": "28.9000",
            "4. close": "29.1200",
            "5. volume": "8726964"
        },
        "2024-10-29": {
            "1. open": "31.6800",
            "2. high": "31.8800",
            "3. low": "30.1200",
            "4. close": "30.2500",
            "5. volume": "6359759"
        },
        "2024-10-28": {
            "1. open": "30.4700",
            "2. high": "31.5100",
            "3. low": "30.1000",
            "4. close": "31.2700",
            "5. volume": "5907923"
        },
        "2024-10-25": {
            "1. open": "29.8700",
            "2. high": "30.8000",
            "3. low": "29.8200",
            "4. close": "30.4500",
            "5. volume": "4654184"
        },
        "2024-10-24": {
            "1. open": "30.3500",
            "2. high": "30.5300",
            "3. low": "29.8800",
            "4. close": "29.9300",
            "5. volume": "3774169"
        },
        "2024-10-23": {
            "1. open": "30.4900",
            "2. high": "30.9000",
            "3. low": "30.2000",
            "4. close": "30.5100",
            "5. volume": "4365489"
        },
        "2024-10-22": {
            "1. open": "30.0000",
            "2. high": "30.7500",
            "3. low": "29.7600",
            "4. close": "30.4700",
            "5. volume": "5753006"
        },
        "2024-10-21": {
            "1. open": "30.1000",
            "2. high": "30.5700",
            "3. low": "29.5100",
            "4. close": "30.0200",
            "5. volume": "5692105"
        },
        "2024-10-18": {
            "1. open": "29.2100",
            "2. high": "30.6700",
            "3. low": "29.0100",
            "4. close": "29.9500",
            "5. volume": "8159947"
        },
        "2024-10-17": {
            "1. open": "30.2700",
            "2. high": "30.4300",
            "3. low": "29.2500",
            "4. close": "29.2700",
            "5. volume": "6526951"
        },
        "2024-10-16": {
            "1. open": "30.5000",
            "2. high": "30.8700",
            "3. low": "30.0000",
            "4. close": "30.1400",
            "5. volume": "7105667"
        },
        "2024-10-15": {
            "1. open": "31.6500",
            "2. high": "31.6500",
            "3. low": "30.7000",
            "4. close": "30.7000",
            "5. volume": "5652017"
        },
        "2024-10-14": {
            "1. open": "32.0300",
            "2. high": "32.1600",
            "3. low": "30.8900",
            "4. close": "31.8000",
            "5. volume": "5020551"
        },
        "2024-10-11": {
            "1. open": "32.8500",
            "2. high": "32.8500",
            "3. low": "31.5100",
            "4. close": "31.8800",
            "5. volume": "3612769"
        },
        "2024-10-10": {
            "1. open": "32.8200",
            "2. high": "33.8500",
            "3. low": "32.0000",
            "4. close": "32.8200",
            "5. volume": "6369345"
        },
        "2024-10-09": {
            "1. open": "36.0000",
            "2. high": "36.0000",
            "3. low": "32.8200",
            "4. close": "32.8200",
            "5. volume": "12982158"
        },
        "2024-10-08": {
            "1. open": "38.9500",
            "2. high": "38.9500",
            "3. low": "34.0000",
            "4. close": "36.4700",
            "5. volume": "13064203"
        },
        "2024-09-30": {
            "1. open": "33.6000",
            "2. high": "35.4200",
            "3. low": "33.4000",
            "4. close": "35.4100",
            "5. volume": "11377677"
        },
        "2024-09-27": {
            "1. open": "30.2000",
            "2. high": "32.3000",
            "3. low": "30.1500",
            "4. close": "32.2000",
            "5. volume": "6304890"
        },
        "2024-09-26": {
            "1. open": "27.2900",
            "2. high": "29.7600",
            "3. low": "27.1900",
            "4. close": "29.7000",
            "5. volume": "8875111"
        },
        "2024-09-25": {
            "1. open": "27.4900",
            "2. high": "28.3000",
            "3. low": "27.1600",
            "4. close": "27.3300",
            "5. volume": "5937119"
        },
        "2024-09-24": {
            "1. open": "26.7000",
            "2. high": "27.0800",
            "3. low": "26.0000",
            "4. close": "27.0500",
            "5. volume": "5660171"
        },
        "2024-09-23": {
            "1. open": "25.6400",
            "2. high": "26.7400",
            "3. low": "25.5300",
            "4. close": "26.4900",
            "5. volume": "5068399"
        },
        "2024-09-20": {
            "1. open": "25.8400",
            "2. high": "25.9100",
            "3. low": "25.3600",
            "4. close": "25.6700",
            "5. volume": "2717270"
        },
        "2024-09-19": {
            "1. open": "25.6000",
            "2. high": "26.4900",
            "3. low": "25.5000",
            "4. close": "25.9200",
            "5. volume": "3136107"
        },
        "2024-09-18": {
            "1. open": "25.4700",
            "2. high": "25.6000",
            "3. low": "25.0100",
            "4. close": "25.2800",
            "5. volume": "2125936"
        },
        "2024-09-13": {
            "1. open": "25.9600",
            "2. high": "25.9800",
            "3. low": "25.5000",
            "4. close": "25.5000",
            "5. volume": "2456451"
        },
        "2024-09-12": {
            "1. open": "26.5600",
            "2. high": "26.6500",
            "3. low": "26.0100",
            "4. close": "26.0200",
            "5. volume": "2222753"
        },
        "2024-09-11": {
            "1. open": "25.5700",
            "2. high": "26.7500",
            "3. low": "25.5200",
            "4. close": "26.5300",
            "5. volume": "4871236"
        },
        "2024-09-10": {
            "1. open": "26.0300",
            "2. high": "26.0300",
            "3. low": "25.3300",
            "4. close": "25.6500",
            "5. volume": "3066129"
        },
        "2024-09-09": {
            "1. open": "25.9200",
            "2. high": "26.2500",
            "3. low": "25.8200",
            "4. close": "25.9300",
            "5. volume": "2606279"
        },
        "2024-09-06": {
            "1. open": "26.4000",
            "2. high": "26.6500",
            "3. low": "26.0800",
            "4. close": "26.1100",
            "5. volume": "2200859"
        },
        "2024-09-05": {
            "1. open": "25.7800",
            "2. high": "26.4500",
            "3. low": "25.7800",
            "4. close": "26.3900",
            "5. volume": "2949487"
        },
        "2024-09-04": {
            "1. open": "26.0100",
            "2. high": "26.4000",
            "3. low": "25.8700",
            "4. close": "25.9500",
            "5. volume": "2517657"
        },
        "2024-09-03": {
            "1. open": "25.6000",
            "2. high": "26.4400",
            "3. low": "25.6000",
            "4. close": "26.1300",
            "5. volume": "2698640"
        },
        "2024-09-02": {
            "1. open": "26.5700",
            "2. high": "26.6800",
            "3. low": "25.4500",
            "4. close": "25.7100",
            "5. volume": "5219573"
        }
    }
}